PyamilySeq/Group_Compare.py
PyamilySeq/Group_Extractor.py
PyamilySeq/Group_Sizes.py
PyamilySeq/Group_Splitter.py
PyamilySeq/Group_Summary.py
PyamilySeq/PyamilySeq.py
PyamilySeq/PyamilySeq_Genus.py
PyamilySeq/PyamilySeq_Species.py
PyamilySeq/Seq_Combiner.py
PyamilySeq/Seq_Extractor.py
PyamilySeq/Seq_Finder.py
PyamilySeq/__init__.py
PyamilySeq/clusterings.py
PyamilySeq/config.py
PyamilySeq/constants.py
PyamilySeq/utils.py
pyamilyseq-1.3.2.dist-info/licenses/LICENSE
pyamilyseq-1.3.2.dist-info/METADATA
pyamilyseq-1.3.2.dist-info/WHEEL
pyamilyseq-1.3.2.dist-info/entry_points.txt
pyamilyseq-1.3.2.dist-info/top_level.txt
pyamilyseq-1.3.2.dist-info/RECORD
