Metadata-Version: 2.4
Name: PyamilySeq
Version: 1.3.2
Summary: PyamilySeq - A a tool to investigate sequence-based gene groups identified by clustering methods such as CD-HIT, DIAMOND, BLAST or MMseqs2.
Author-email: Nicholas Dimonaco <nicholas@dimonaco.co.uk>
License:                     GNU GENERAL PUBLIC LICENSE
Project-URL: Homepage, https://github.com/NickJD/PyamilySeq
Project-URL: Bug Tracker, https://github.com/NickJD/PyamilySeq/issues
Keywords: Pangenomics,Sequence Clustering,Gene Families
Classifier: Programming Language :: Python :: 3
Classifier: License :: OSI Approved :: GNU General Public License v3 (GPLv3)
Classifier: Operating System :: OS Independent
Requires-Python: >=3.10
License-File: LICENSE
Dynamic: license-file
